{
  "name": "Morning Nudge → Slack DM mit Top-Aufgabe",
  "nodes": [
    {
      "parameters": {
        "rule": {
          "interval": [
            {
              "triggerAtHour": 8,
              "triggerAtMinute": 0
            }
          ]
        }
      },
      "id": "schedule",
      "name": "Täglich 8:00",
      "type": "n8n-nodes-base.scheduleTrigger",
      "typeVersion": 1.2,
      "position": [0, 300]
    },
    {
      "parameters": {
        "url": "={{ $env.SUPABASE_URL }}/rest/v1/personen?slack_id=not.is.null&select=id,name,slack_id",
        "sendHeaders": true,
        "headerParameters": {
          "parameters": [
            { "name": "apikey", "value": "={{ $env.SUPABASE_KEY }}" },
            { "name": "Authorization", "value": "=Bearer {{ $env.SUPABASE_KEY }}" }
          ]
        },
        "options": {}
      },
      "id": "load-personen",
      "name": "Personen mit Slack-ID laden",
      "type": "n8n-nodes-base.httpRequest",
      "typeVersion": 4.2,
      "position": [250, 300]
    },
    {
      "parameters": {
        "url": "={{ $env.SUPABASE_URL }}/rest/v1/aufgaben?status=in.(neu,backlog,aktiv)&select=id,pid,titel,prio,dl,status",
        "sendHeaders": true,
        "headerParameters": {
          "parameters": [
            { "name": "apikey", "value": "={{ $env.SUPABASE_KEY }}" },
            { "name": "Authorization", "value": "=Bearer {{ $env.SUPABASE_KEY }}" }
          ]
        },
        "options": {}
      },
      "id": "load-aufgaben",
      "name": "Offene Aufgaben laden",
      "type": "n8n-nodes-base.httpRequest",
      "typeVersion": 4.2,
      "position": [250, 500]
    },
    {
      "parameters": {
        "mode": "combine",
        "mergeByFields": {
          "values": []
        },
        "combinationMode": "mergeByPosition",
        "options": {}
      },
      "id": "merge",
      "name": "Zusammenführen",
      "type": "n8n-nodes-base.merge",
      "typeVersion": 3,
      "position": [500, 400]
    },
    {
      "parameters": {
        "jsCode": "const personen = $input.first().json;\nconst aufgaben = items.length > 1 ? $input.last().json : [];\nconst pList = Array.isArray(personen) ? personen : [personen];\nconst aList = Array.isArray(aufgaben) ? aufgaben : [aufgaben];\n\nconst APP_URL = $env.APP_URL || 'https://ludwig-a11y.github.io/halleluja-os/';\nconst today = new Date().toISOString().slice(0, 10);\nconst prioRank = { P1: 0, P2: 1, P3: 2 };\n\nconst results = [];\n\nfor (const p of pList) {\n  if (!p.slack_id) continue;\n\n  const meine = aList.filter(a => String(a.pid) === String(p.id));\n\n  // Sortiere: aktive zuerst, dann Prio (P1>P2>P3), dann Deadline\n  meine.sort((a, b) => {\n    if (a.status === 'aktiv' && b.status !== 'aktiv') return -1;\n    if (b.status === 'aktiv' && a.status !== 'aktiv') return 1;\n    const pp = (prioRank[a.prio] ?? 3) - (prioRank[b.prio] ?? 3);\n    if (pp !== 0) return pp;\n    if (a.dl && b.dl) return a.dl.localeCompare(b.dl);\n    if (a.dl) return -1;\n    if (b.dl) return 1;\n    return 0;\n  });\n\n  if (meine.length === 0) {\n    results.push({\n      json: {\n        channel: p.slack_id,\n        text: `☀️ Guten Morgen, ${p.name}!\\n\\nKeine offenen Aufgaben — genieß den Tag! 🎉\\n<${APP_URL}|Halleluja OS öffnen>`\n      }\n    });\n    continue;\n  }\n\n  const top = meine[0];\n  const prioEmoji = top.prio === 'P1' ? '🔴' : top.prio === 'P2' ? '🟡' : top.prio === 'P3' ? '🔵' : '⚪';\n  const statusHint = top.status === 'aktiv' ? ' _(läuft bereits)_' : '';\n\n  let dlInfo = '';\n  if (top.dl) {\n    const dlDate = new Date(top.dl + 'T12:00:00');\n    const diff = Math.ceil((dlDate - new Date(today + 'T12:00:00')) / 86400000);\n    if (diff === 0) dlInfo = '⏰ Fällig: heute';\n    else if (diff === 1) dlInfo = '⏰ Fällig: morgen';\n    else if (diff < 0) dlInfo = '🔴 Überfällig seit ' + Math.abs(diff) + ' Tag' + (Math.abs(diff) > 1 ? 'en' : '');\n    else dlInfo = '📅 Fällig in ' + diff + ' Tagen';\n  }\n\n  const deepLink = `${APP_URL}#task=${top.id}`;\n  let msg = `☀️ Guten Morgen, ${p.name}!\\n\\n${prioEmoji} *Dein wichtigstes To-Do:*\\n> *${top.titel}*${statusHint}`;\n  if (dlInfo) msg += `\\n> ${dlInfo}`;\n  msg += `\\n\\n<${deepLink}|Hier starten →>`;\n\n  const p1Count = meine.filter(a => a.prio === 'P1').length;\n  const totalCount = meine.length;\n  const summary = [];\n  if (p1Count > 1) summary.push(p1Count + ' P1s offen');\n  if (totalCount > 1) summary.push(totalCount + ' Aufgaben gesamt');\n  if (summary.length) msg += `\\n\\n_${summary.join(' · ')}_`;\n\n  results.push({ json: { channel: p.slack_id, text: msg } });\n}\n\nreturn results;"
      },
      "id": "format-messages",
      "name": "Nachrichten pro Person",
      "type": "n8n-nodes-base.code",
      "typeVersion": 2,
      "position": [750, 400],
      "notesInFlow": true,
      "notes": "Pro Person: wichtigste Aufgabe (aktiv > P1 > P2 > P3 > Deadline). Immer eine Nachricht senden."
    },
    {
      "parameters": {
        "method": "POST",
        "url": "https://slack.com/api/chat.postMessage",
        "authentication": "predefinedCredentialType",
        "nodeCredentialType": "slackOAuth2Api",
        "sendHeaders": true,
        "headerParameters": {
          "parameters": [
            { "name": "Content-Type", "value": "application/json" }
          ]
        },
        "sendBody": true,
        "specifyBody": "json",
        "jsonBody": "={{ JSON.stringify({ channel: $json.channel, text: $json.text, unfurl_links: false }) }}",
        "options": {}
      },
      "id": "slack-dm",
      "name": "Slack DM senden",
      "type": "n8n-nodes-base.httpRequest",
      "typeVersion": 4.2,
      "position": [1000, 400]
    }
  ],
  "connections": {
    "Täglich 8:00": {
      "main": [
        [
          { "node": "Personen mit Slack-ID laden", "type": "main", "index": 0 },
          { "node": "Offene Aufgaben laden", "type": "main", "index": 0 }
        ]
      ]
    },
    "Personen mit Slack-ID laden": {
      "main": [
        [{ "node": "Zusammenführen", "type": "main", "index": 0 }]
      ]
    },
    "Offene Aufgaben laden": {
      "main": [
        [{ "node": "Zusammenführen", "type": "main", "index": 1 }]
      ]
    },
    "Zusammenführen": {
      "main": [
        [{ "node": "Nachrichten pro Person", "type": "main", "index": 0 }]
      ]
    },
    "Nachrichten pro Person": {
      "main": [
        [{ "node": "Slack DM senden", "type": "main", "index": 0 }]
      ]
    }
  },
  "settings": {
    "executionOrder": "v1"
  }
}
